setup.py
OAIPMHScraper.egg-info/PKG-INFO
OAIPMHScraper.egg-info/SOURCES.txt
OAIPMHScraper.egg-info/dependency_links.txt
OAIPMHScraper.egg-info/requires.txt
OAIPMHScraper.egg-info/top_level.txt
bin/oaipmh_file_downloader
oaipmhscraper/__init__.py
oaipmhscraper/eprints_harvest.py
oaipmhscraper/eprintsxml.py
oaipmhscraper/oaipmh_scraper.py