Metadata-Version: 1.0
Name: OAIPMHScraper
Version: 0.4.1
Summary: OAIPMH Scraper - grabs and sync's metadata from an OAIPMH target and stores it locally in a Pairtree structure.
Home-page: UNKNOWN
Author: Ben O'Steen
Author-email: bosteen@gmail.com
License: UNKNOWN
Platform: UNKNOWN
